{
  "basics": {
    "name": "Ethan Chee",
    "label": "Student",
    "picture": "https://ethancheez.github.io/images/ethan.jpg",
    "email": "ethanwc@hawaii.edu",
    "phone": "",
    "website": "https://ethancheez.github.io",
    "summary": "I am studying for a B.S. in Computer Engineering in the College of Engineering at the University of Hawaii. I expect to graduate in Fall, 2022.",
    "location": {
      "address": "",
      "postalCode": "96817",
      "city": "Honolulu",
      "countryCode": "USA",
      "region": "Hawaii"
    },
    "profiles": [
      {
        "network": "github",
        "username": "ethancheez",
        "url": "https://github.com/ethancheez"
      },
      {
        "network": "linkedin",
        "username": "ethancheez",
        "url": "https://linkedin.com/in/ethan-cheez"
      },
      {
        "network": "instagram",
        "username": "ethan._.cheez",
        "url": "http://instagram.com/ethan._.cheez"
      }
    ]
  },
  "interests": [
    {
      "name": "Electrical Engineering",
      "keywords": [
        "Arduino",
        "Circuits"
      ]
    },
    {
      "name": "Software Engineering",
      "keywords": [
        "Python",
        "Java",
        "C/C++"
      ]
    },
    {
      "name": "Artificial Intelligence",
      "keywords": [
        "Robotics",
        "Autonomy"
      ]
    }
  ],
  "skills": [
    {
      "name": "Languages",
      "level": "",
      "keywords": [
        "C",
        "C++",
        "Java",
        "LaTeX"
      ]
    },
    {
      "name": "Toolsets/OS",
      "level": "",
      "keywords": [
        "Windows",
        "Ubuntu",
        "Git/GitHub"
      ]
    },
    {
      "name": "Applications",
      "level": "",
      "keywords": [
        "Adobe Photoshop",
        "Excel",
        "SketchUp"
      ]
    }
  ],
  "education": [
    {
      "institution": "University of Hawaii at Mānoa, Honolulu, HI",
      "area": "Computer Engineering (expected Fall, 2022)",
      "studyType": "B.S.",
      "startDate": "2019-08-01",
      "endDate": "Present",
      "gpa": "3.89",
      "courses": [
      ]
    }
  ],
  "work": [
    {
      "company": "UH Mānoa Chemistry Department",
      "position": "Learning Assistant",
      "website": "",
      "startDate": "2020-01-01",
      "endDate": "Present",
      "summary": "Learning Assistant for the course CHEM 162: General Chemistry II. Leading a recitation class and assisting the students during office hours.",
      "highlights": [
      ]
    },
    {
      "company": "UH Mānoa Department of Engineering",
      "position": "Teaching Assistant",
      "website": "",
      "startDate": "2020-08-01",
      "endDate": "2020-12-18",
      "summary": "Teaching Assistant for the course EE 160: Programming for Engineers. Leading the lab portion of the course.",
      "highlights": [
      ]
    }
  ],
  "volunteer": [
    {
      "organization": "Hawaii Undergraduate Initiative",
      "website": "",
      "position": "Peer Mentor",
      "startDate": "2020-06-01",
      "endDate": "2020-12-18",
      "summary": "Peer mentor for the incoming freshman into the University of Hawaiʻi at Mānoa",
      "highlights": [
      ]
    },
    {
      "organization": "808 Cleanups",
      "website": "",
      "position": "Volunteer",
      "startDate": "2019-12-01",
      "endDate": "2020-01-31",
      "summary": "Participated in cleanups around the island, including beaches and parks.",
      "highlights": [
      ]
    },
    {
      "organization": "VEX Robotics",
      "website": "",
      "position": "Referee and Inspection Team",
      "startDate": "2019-11-23",
      "endDate": "2019-11-23",
      "summary": "Helped setup for the ECUH VEX Robotics Tournament and was part of the robot inspection team and referee during tournament matches.",
      "highlights": [
      ]
    }
  ],
  "awards": [
    {
      "title": "University of Hawaii at Mānoa Dean's List",
      "date": "",
      "awarder": "",
      "summary": "Fall 2019, Spring 2020, Fall 2020"
    },
    {
      "title": "Academic, STEM, and CTE Honors",
      "date": "May 2019",
      "awarder": "Moanalua High School",
      "summary": "Honors awarded during graduation for the completion of two AP courses with four years of math and science (academic), completion of the STEM pathway (STEM), and completion of a capstone project (CTE)."
    },
    {
      "title": "HAS Senior 1st Category Award: 1st Place - Robotics and Intelligent Machines",
      "date": "April 2019",
      "awarder": "Hawaii Academy of Science",
      "summary": "First place award for the project: Lightweight Wearable Device to Improve Safety for the Blind during the 62nd Hawaii State Science and Engineering Fair"
    },
    {
      "title": "2019 Research Directorate - 2nd Place",
      "date": "April 2019",
      "awarder": "National Security Agency",
      "summary": "Awarded during the 62nd Hawaii State Science and Engineering Fair"
    },
    {
      "title": "Hawaii Chapter Award",
      "date": "April 2019",
      "awarder": "Illuminating Engineering Society",
      "summary": "Awarded during the 62nd Hawaii State Science and Engineering Fair"
    },
    {
      "title": "Hawaiian Eye Foundation Award",
      "date": "April 2019",
      "awarder": "Hawaiian Eye Foundation",
      "summary": "Awarded during the 62nd Hawaii State Science and Engineering Fair"
    }
  ],
  "references": [
    {
      "name": "Available upon request",
      "reference": ""
    }
  ]
}
